AUTHORS
COPYING
ChangeLog
MANIFEST.in
README.rst
bindep.txt
requirements.txt
setup.cfg
setup.py
test-requirements.txt
tox.ini
doc/Makefile
doc/source/api.rst
doc/source/conf.py
doc/source/examples.rst
doc/source/index.rst
doc/source/install.rst
jenkins/__init__.py
jenkins/plugins.py
jenkins/version.py
jenkins_python_lib.egg-info/PKG-INFO
jenkins_python_lib.egg-info/SOURCES.txt
jenkins_python_lib.egg-info/dependency_links.txt
jenkins_python_lib.egg-info/not-zip-safe
jenkins_python_lib.egg-info/pbr.json
jenkins_python_lib.egg-info/requires.txt
jenkins_python_lib.egg-info/top_level.txt
tests/__init__.py
tests/base.py
tests/helper.py
tests/test_build.py
tests/test_check_jenkinsfile_syntax.py
tests/test_credential.py
tests/test_info.py
tests/test_jenkins.py
tests/test_jenkins_sockets.py
tests/test_job_folder.py
tests/test_node.py
tests/test_plugins.py
tests/test_promotion.py
tests/test_queue.py
tests/test_quiet_down.py
tests/test_rest_endpoints.py
tests/test_script.py
tests/test_version.py
tests/test_view.py
tests/test_whoami.py
tests/jobs/__init__.py
tests/jobs/base.py
tests/jobs/test_assert.py
tests/jobs/test_build.py
tests/jobs/test_config.py
tests/jobs/test_copy.py
tests/jobs/test_count.py
tests/jobs/test_create.py
tests/jobs/test_debug.py
tests/jobs/test_delete.py
tests/jobs/test_disable.py
tests/jobs/test_enable.py
tests/jobs/test_get.py
tests/jobs/test_getall.py
tests/jobs/test_info.py
tests/jobs/test_name.py
tests/jobs/test_reconfig.py
tests/jobs/test_rename.py
tests/jobs/test_set_next_build_number.py