Metadata-Version: 2.1
Name: jenkins-python-lib
Version: 0.0.1.dev2
Summary: Python bindings for the remote Jenkins API
Home-page: https://opendev.org/jjb/python-jenkins
Author: Ken Conley
Author-email: kwc@willowgarage.com
Maintainer: Python-Jenkins Developers
Maintainer-email: python-jenkins-developers@lists.launchpad.net
License: BSD
Project-URL: Documentation, https://python-jenkins.readthedocs.io/
Platform: UNKNOWN
Classifier: Topic :: Utilities
Classifier: Intended Audience :: Developers
Classifier: Intended Audience :: Information Technology
Classifier: Intended Audience :: System Administrators
Classifier: Environment :: Console
Classifier: License :: OSI Approved :: BSD License
Classifier: Operating System :: OS Independent
Classifier: Programming Language :: Python
Classifier: Programming Language :: Python :: 2
Classifier: Programming Language :: Python :: 2.7
Classifier: Programming Language :: Python :: 3
Classifier: Programming Language :: Python :: 3.4
Classifier: Programming Language :: Python :: 3.5
Classifier: Programming Language :: Python :: 3.6
License-File: COPYING
License-File: AUTHORS
